khnum/__init__.py
khnum/datapoint.py
khnum/khnum.py
khnum-0.0.3.dist-info/LICENSE
khnum-0.0.3.dist-info/METADATA
khnum-0.0.3.dist-info/WHEEL
khnum-0.0.3.dist-info/top_level.txt
khnum-0.0.3.dist-info/RECORD
