Metadata-Version: 2.1
Name: khnum
Version: 0.0.3
Summary: Human readable numbers
Home-page: https://github.com/siznax/khnum/
Author: siznax
Author-email: steve@siznax.net
License: UNKNOWN
Platform: UNKNOWN
Classifier: Programming Language :: Python :: 3
Classifier: License :: OSI Approved :: MIT License
Classifier: Operating System :: OS Independent
